strmdck/__init__.py
strmdck/device.py
strmdck/device_manager.py
strmdck/utils.py
strmdck/devices/__init__.py
strmdck/devices/ulanzi_d200.py
strmdck-0.1.0rc1.dist-info/licenses/LICENSE
strmdck-0.1.0rc1.dist-info/METADATA
strmdck-0.1.0rc1.dist-info/WHEEL
strmdck-0.1.0rc1.dist-info/top_level.txt
strmdck-0.1.0rc1.dist-info/RECORD
