Metadata-Version: 2.4
Name: strmdck
Version: 0.1.0rc1
Summary: Python library to control Stream Deck-like devices
Author: redphx
License: MIT License
Project-URL: Homepage, https://github.com/redphx/strmdck
Project-URL: Issues, https://github.com/redphx/strmdck/issues
Project-URL: Repository, https://github.com/redphx/strmdck.git
Keywords: streamdeck,stream deck,stream-deck
Requires-Python: >=3.9
License-File: LICENSE
Requires-Dist: construct==2.10.70
Requires-Dist: pytest==8.3.4
Requires-Dist: hidapi==0.14.0.post4
Dynamic: license-file
